[
    {
        "%vlocity_namespace%__DomainObjectAPIName__c": "Lead",
        "%vlocity_namespace%__DomainObjectCreationOrder__c": 1,
        "%vlocity_namespace%__DomainObjectFieldAPIName__c": "ConvertedOpportunityId",
        "%vlocity_namespace%__GlobalKey__c": "856e1b41-7da6-0c7f-b5f8-444864fe58c7",
        "%vlocity_namespace%__InterfaceFieldAPIName__c": "objectList:OpportunityId",
        "%vlocity_namespace%__IsDisabled__c": true,
        "%vlocity_namespace%__IsRequiredForUpsert__c": false,
        "%vlocity_namespace%__MapId__c": "DRNewConnectUpdateLeadCustom5233",
        "%vlocity_namespace%__OMplusSyncEnabled__c": true,
        "%vlocity_namespace%__UpsertKey__c": false,
        "Name": "DRNewConnectUpdateLead",
        "VlocityDataPackType": "SObject",
        "VlocityRecordSObjectType": "%vlocity_namespace%__DRMapItem__c"
    },
    {
        "%vlocity_namespace%__DomainObjectAPIName__c": "Lead",
        "%vlocity_namespace%__DomainObjectCreationOrder__c": 1,
        "%vlocity_namespace%__DomainObjectFieldAPIName__c": "Id",
        "%vlocity_namespace%__GlobalKey__c": "dfe98aa2-77ef-99f9-ac30-9ed5d5fca3aa",
        "%vlocity_namespace%__InterfaceFieldAPIName__c": "DRId_Lead",
        "%vlocity_namespace%__IsDisabled__c": false,
        "%vlocity_namespace%__IsRequiredForUpsert__c": false,
        "%vlocity_namespace%__MapId__c": "DRNewConnectUpdateLeadCustom128",
        "%vlocity_namespace%__OMplusSyncEnabled__c": true,
        "%vlocity_namespace%__UpsertKey__c": true,
        "Name": "DRNewConnectUpdateLead",
        "VlocityDataPackType": "SObject",
        "VlocityRecordSObjectType": "%vlocity_namespace%__DRMapItem__c"
    },
    {
        "%vlocity_namespace%__ConfigurationValue__c": "FAKEMAPPING",
        "%vlocity_namespace%__DomainObjectAPIName__c": "Lead",
        "%vlocity_namespace%__DomainObjectCreationOrder__c": 1,
        "%vlocity_namespace%__DomainObjectFieldAPIName__c": "Id",
        "%vlocity_namespace%__FilterOperator__c": "=",
        "%vlocity_namespace%__GlobalKey__c": "459824e6-805a-35d6-7ce7-10f13fcadaed",
        "%vlocity_namespace%__IsDisabled__c": true,
        "%vlocity_namespace%__IsRequiredForUpsert__c": false,
        "%vlocity_namespace%__MapId__c": "DRNewConnectUpdateLeadCustom4838",
        "%vlocity_namespace%__OMplusSyncEnabled__c": true,
        "%vlocity_namespace%__UpsertKey__c": false,
        "Name": "DRNewConnectUpdateLead",
        "VlocityDataPackType": "SObject",
        "VlocityRecordSObjectType": "%vlocity_namespace%__DRMapItem__c"
    },
    {
        "%vlocity_namespace%__DefaultValue__c": "Converted",
        "%vlocity_namespace%__DomainObjectAPIName__c": "Lead",
        "%vlocity_namespace%__DomainObjectCreationOrder__c": 1,
        "%vlocity_namespace%__DomainObjectFieldAPIName__c": "Status",
        "%vlocity_namespace%__GlobalKey__c": "e4a8bae7-fcd9-ffbc-e85c-22ffdaa0e9c9",
        "%vlocity_namespace%__IsDisabled__c": false,
        "%vlocity_namespace%__IsRequiredForUpsert__c": false,
        "%vlocity_namespace%__MapId__c": "DRNewConnectUpdateLeadCustom7421",
        "%vlocity_namespace%__OMplusSyncEnabled__c": true,
        "%vlocity_namespace%__UpsertKey__c": false,
        "Name": "DRNewConnectUpdateLead",
        "VlocityDataPackType": "SObject",
        "VlocityRecordSObjectType": "%vlocity_namespace%__DRMapItem__c"
    }
]